pyinim/__init__.py
pyinim/inim_cloud.py
pyinim/cloud/__init__.py
pyinim/cloud/abc.py
pyinim/cloud/exceptions.py
pyinim/cloud/resolver.py
pyinim/cloud/types/__init__.py
pyinim/cloud/types/devices.py
pyinim/cloud/types/token.py
pyinim/examples/__init__.py
pyinim/examples/poc.py
pyinim-0.0.20.dist-info/licenses/LICENSE
pyinim-0.0.20.dist-info/METADATA
pyinim-0.0.20.dist-info/WHEEL
pyinim-0.0.20.dist-info/top_level.txt
pyinim-0.0.20.dist-info/RECORD
