Metadata-Version: 2.4
Name: pyinim
Version: 0.0.20
Summary: A Inim Cloud API client
Home-page: https://github.com/nidble/pyinim
Author: Antonino Bertulla
Author-email: Antonino Bertulla <abertulla@email.address>
Project-URL: Homepage, https://github.com/nidble/pyinim
Project-URL: Issues, https://github.com/nidble/pyinim/issues
Classifier: Programming Language :: Python :: 3
Classifier: Operating System :: OS Independent
Requires-Python: >=3.8
License-File: LICENSE
Requires-Dist: aiohttp<4.0.0,>=3.7.4
Provides-Extra: dotenv
Requires-Dist: python-dotenv>=1.0.1; extra == "dotenv"
Dynamic: license-file
